EmoTFIDF/EmoTFIDF.py
EmoTFIDF/__init__.py
EmoTFIDF/emotions_lex.json
tests/__init__.py
tests/test_emotfidf.py
EmoTFIDF-1.4.2.dist-info/LICENSE
EmoTFIDF-1.4.2.dist-info/METADATA
EmoTFIDF-1.4.2.dist-info/WHEEL
EmoTFIDF-1.4.2.dist-info/top_level.txt
EmoTFIDF-1.4.2.dist-info/RECORD
