Metadata-Version: 2.1
Name: EmoTFIDF
Version: 1.4.2
Summary: A library to extract emotions using three methods: 1- Lexicon based, counting frequency of emotion, 2- Integrating TFIDF to add context, and 3- Hybrid transformer-TFIDF approach. Note that lexicon license is for research purposes only.
Home-page: https://github.com/mmsa/emotfidf
Author: mmsa12
Author-email: mmsa12@gmail.com
Classifier: Programming Language :: Python :: 3.6
Classifier: License :: OSI Approved :: MIT License
Classifier: Operating System :: OS Independent
Requires-Python: >=3.6
License-File: LICENSE
Requires-Dist: nltk
Requires-Dist: scikit-learn
Requires-Dist: pandas
Requires-Dist: matplotlib
Requires-Dist: seaborn
Requires-Dist: torch
Requires-Dist: transformers
